fulladder.v
module fulladder (sum,carry,a,b,cin);
output sum ,carry;
input a,b,cin;
wire x,y,z;
xor u1(x,a,b);
and u2(y,a,b);
and u3(z,x,cin);
or u4(carry,y,z);
xor u5(sum,x,cin);  
endmodule

fulladder_tb.v
`timescale 10ns/10ps
`include "fulladder.v"
module fulladder_tb ();
reg a,b,cin;
wire sum ,carry;
fulladder init(
    .a(a),
    .b(b),
    .cin(cin),
    .sum(sum),
    .carry(carry)
);
initial $dumpfile("fulladder_tb.vcd");
initial $dumpvars(0, fulladder_tb);
initial begin
     a = 0;
     b = 0;
     cin = 0;
     #10;
     a = 0;
     b = 0;
     cin = 1;
     #10;
     a = 0;
     b = 1;
     cin = 0;
     #10;
     a = 0;
     b = 1;
     cin = 1;
     #10;
     a = 1;
     b = 0;
     cin = 0;
     #10;
     a = 1;
     b = 0;
     cin = 1;
     #10;
     a = 1;
     b = 1;
     cin = 0;
     #10;
     a = 1;
     b = 1;
     cin = 1;
     #10;
     #10 $finish ;

end
initial
begin
    $display("A\tB\tCin\tSum\tCarry");
    $monitor("%b\t%b\t%b\t%b\t%b",a,b,cin,sum,carry);
end
    
endmodule

fulladder_tb.vcd
$date
	Wed Nov 25 21:56:56 2020
$end
$version
	Icarus Verilog
$end
$timescale
	10ps
$end
$scope module fulladder_tb $end
$var wire 1 ! sum $end
$var wire 1 " carry $end
$var reg 1 # a $end
$var reg 1 $ b $end
$var reg 1 % cin $end
$scope module init $end
$var wire 1 # a $end
$var wire 1 $ b $end
$var wire 1 " carry $end
$var wire 1 % cin $end
$var wire 1 ! sum $end
$var wire 1 & x $end
$var wire 1 ' y $end
$var wire 1 ( z $end
$upscope $end
$upscope $end
$enddefinitions $end
#0
$dumpvars
0(
0'
0&
0%
0$
0#
0"
0!
$end
#10000
1!
1%
#20000
1&
0%
1$
#30000
1"
1(
0!
1%
#40000
0"
0(
1!
0%
0$
1#
#50000
1"
1(
0!
1%
#60000
0(
0&
1'
0%
1$
#70000
1!
1%
