Mux16X1.v
module Mux2X1 (
    output y_out,
    input i1,
    input i0,sel 
);
wire sel_bar,y0,y1;
not(sel_bar,sel);
and(y0,i0,sel_bar);
and(y1,i1,sel);
or(y_out,y0,y1);   
endmodule


module MUX4X1 (
    output y_out,
    input i3,i2,i1,i0,sel1,sel0
);
wire y_M0,y_M1;
Mux2X1 M0(y_M0,i0,i1,sel1);
Mux2X1 M1(y_M1,i2,i3,sel1);
Mux2X1 M2(y_out,y_M1,y_M1,sel0);  
endmodule


module Mux8X1 (
    output y_out,
    input i7,i6,i5,i4,i3,i2,i1,i0,sel2,sel1,sel0
);
wire y_M0,y_M1;
MUX4X1 M0(y_M0,i3,i2,i1,i0,sel1,sel0);
MUX4X1 M1(y_M1,i7,i6,i5,i4,sel1,sel0);
Mux2X1 M2(y_out,y_M0,y_M1,sel2);   
endmodule


module Mux16X1 (
    output y_out,
    input i15,i14,i13,i12,i11,i10,i9,i8,i7,i6,i5,i4,i3,i2,i1,i0,sel3,sel2,sel1,sel0
);
wire y_M0,y_M1;
Mux8X1 M0(y_M0,i7,i6,i5,i4,i3,i2,i1,i0,sel2,sel1,sel0);
Mux8X1 M1(y_M1,i15,i14,i13,i12,i11,i10,i9,i8,sel2,sel1,sel0);
Mux2X1 M2(y_out,y_M0,y_M1,sel3);  
endmodule

Mux16X1_tb.v
`timescale 1ns/1ps
`include "Mux16X1.v"
module Mux16X1_tb ();
reg i0,i1,i2,i3,i4,i5,i6,i7,i8,i9,i10,i11,i12,i13,i14,i15,sel3,sel2,sel1,sel0;
wire y_out;
Mux16X1 init(.i0(i0),
    .i1(i1),
    .i2(i2),
    .i3(i3),
    .i4(i4),
    .i5(i5),
    .i6(i6),
    .i7(i7),
    .i8(i8),
    .i9(i9),
    .i10(i10),
    .i11(i11),
    .i12(i12),
    .i13(i13),
    .i14(i14),
    .i15(i15),
    .sel3(sel3),
    .sel2(sel2),
    .sel1(sel1),
    .sel0(sel0),
    .y_out(y_out));

always #5 i15=~i15;
always #10 i14=~i14;
always #15 i13=~i13;
always #20 i12=~i12;
always #25 i11=~i11;
always #30 i10=~i10;
always #25 i9=~i9;
always #40 i8=~i8;
always #45 i7=~i7;
always #50 i6=~i6;
always #55 i5=~i5;
always #60 i4=~i4;
always #65 i3=~i3;
always #70 i2=~i2;
always #75 i1=~i1;
always #80 i0=~i0;
always #85 sel0=~sel0;
always #90 sel1=~sel1;
always #95 sel2=~sel2;
always #100 sel3=~sel3;

initial $dumpfile("Mux16X1_tb.vcd");
initial $dumpvars(0, Mux16X1_tb);
initial
begin
    sel3=1'b0;
    sel2=1'b0;
    sel1=1'b0;
    sel0=1'b0;
    i0=1'b0;
    i1=1'b0;
    i2=1'b0;
    i3=1'b0;
    i4=1'b0;
    i5=1'b0;
    i6=1'b0;
    i7=1'b0;
    i8=1'b0;
    i9=1'b0;
    i10=1'b0;
    i11=1'b0;
    i12=1'b0;
    i13=1'b0;
    i14=1'b0;
    i15=1'b0;
    #500 $finish;

end
initial
begin
    $display ("Sel3\tSel2\tSel1\tSel0\tI0\tI1\tI2\tI3\tI4\tI5\tI6\tI7\tI8\tI9\tI10\tI11\tI12\tI13\tI14\tI15\tOutout");
    $monitor( "%b\t%b\t%b\t%b\t%b\t%b\t%b\t%b\t%b\t%b\t%b\t%b\t%b\t%b\t%b\t%b\t%b\t%b\t%b\t%b\t%b",sel3, sel2, sel1, sel0, i0, i1, i2, i3, i4, i5, i6, i7, i8, i9, i10, i11, i12, i13, i14, i15,  y_out);

end
endmodule

Mux16X1_tb.vcd
$date
	Fri Nov 27 09:36:04 2020
$end
$version
	Icarus Verilog
$end
$timescale
	1ps
$end
$scope module Mux16X1_tb $end
$var wire 1 ! y_out $end
$var reg 1 " i0 $end
$var reg 1 # i1 $end
$var reg 1 $ i10 $end
$var reg 1 % i11 $end
$var reg 1 & i12 $end
$var reg 1 ' i13 $end
$var reg 1 ( i14 $end
$var reg 1 ) i15 $end
$var reg 1 * i2 $end
$var reg 1 + i3 $end
$var reg 1 , i4 $end
$var reg 1 - i5 $end
$var reg 1 . i6 $end
$var reg 1 / i7 $end
$var reg 1 0 i8 $end
$var reg 1 1 i9 $end
$var reg 1 2 sel0 $end
$var reg 1 3 sel1 $end
$var reg 1 4 sel2 $end
$var reg 1 5 sel3 $end
$scope module init $end
$var wire 1 " i0 $end
$var wire 1 # i1 $end
$var wire 1 $ i10 $end
$var wire 1 % i11 $end
$var wire 1 & i12 $end
$var wire 1 ' i13 $end
$var wire 1 ( i14 $end
$var wire 1 ) i15 $end
$var wire 1 * i2 $end
$var wire 1 + i3 $end
$var wire 1 , i4 $end
$var wire 1 - i5 $end
$var wire 1 . i6 $end
$var wire 1 / i7 $end
$var wire 1 0 i8 $end
$var wire 1 1 i9 $end
$var wire 1 2 sel0 $end
$var wire 1 3 sel1 $end
$var wire 1 4 sel2 $end
$var wire 1 5 sel3 $end
$var wire 1 ! y_out $end
$var wire 1 6 y_M1 $end
$var wire 1 7 y_M0 $end
$scope module M0 $end
$var wire 1 " i0 $end
$var wire 1 # i1 $end
$var wire 1 * i2 $end
$var wire 1 + i3 $end
$var wire 1 , i4 $end
$var wire 1 - i5 $end
$var wire 1 . i6 $end
$var wire 1 / i7 $end
$var wire 1 2 sel0 $end
$var wire 1 3 sel1 $end
$var wire 1 4 sel2 $end
$var wire 1 7 y_out $end
$var wire 1 8 y_M1 $end
$var wire 1 9 y_M0 $end
$scope module M0 $end
$var wire 1 " i0 $end
$var wire 1 # i1 $end
$var wire 1 * i2 $end
$var wire 1 + i3 $end
$var wire 1 2 sel0 $end
$var wire 1 3 sel1 $end
$var wire 1 9 y_out $end
$var wire 1 : y_M1 $end
$var wire 1 ; y_M0 $end
$scope module M0 $end
$var wire 1 # i0 $end
$var wire 1 " i1 $end
$var wire 1 3 sel $end
$var wire 1 < sel_bar $end
$var wire 1 = y0 $end
$var wire 1 > y1 $end
$var wire 1 ; y_out $end
$upscope $end
$scope module M1 $end
$var wire 1 + i0 $end
$var wire 1 * i1 $end
$var wire 1 3 sel $end
$var wire 1 ? sel_bar $end
$var wire 1 @ y0 $end
$var wire 1 A y1 $end
$var wire 1 : y_out $end
$upscope $end
$scope module M2 $end
$var wire 1 : i0 $end
$var wire 1 : i1 $end
$var wire 1 2 sel $end
$var wire 1 B sel_bar $end
$var wire 1 C y0 $end
$var wire 1 D y1 $end
$var wire 1 9 y_out $end
$upscope $end
$upscope $end
$scope module M1 $end
$var wire 1 , i0 $end
$var wire 1 - i1 $end
$var wire 1 . i2 $end
$var wire 1 / i3 $end
$var wire 1 2 sel0 $end
$var wire 1 3 sel1 $end
$var wire 1 8 y_out $end
$var wire 1 E y_M1 $end
$var wire 1 F y_M0 $end
$scope module M0 $end
$var wire 1 - i0 $end
$var wire 1 , i1 $end
$var wire 1 3 sel $end
$var wire 1 G sel_bar $end
$var wire 1 H y0 $end
$var wire 1 I y1 $end
$var wire 1 F y_out $end
$upscope $end
$scope module M1 $end
$var wire 1 / i0 $end
$var wire 1 . i1 $end
$var wire 1 3 sel $end
$var wire 1 J sel_bar $end
$var wire 1 K y0 $end
$var wire 1 L y1 $end
$var wire 1 E y_out $end
$upscope $end
$scope module M2 $end
$var wire 1 E i0 $end
$var wire 1 E i1 $end
$var wire 1 2 sel $end
$var wire 1 M sel_bar $end
$var wire 1 N y0 $end
$var wire 1 O y1 $end
$var wire 1 8 y_out $end
$upscope $end
$upscope $end
$scope module M2 $end
$var wire 1 8 i0 $end
$var wire 1 9 i1 $end
$var wire 1 4 sel $end
$var wire 1 P sel_bar $end
$var wire 1 Q y0 $end
$var wire 1 R y1 $end
$var wire 1 7 y_out $end
$upscope $end
$upscope $end
$scope module M1 $end
$var wire 1 0 i0 $end
$var wire 1 1 i1 $end
$var wire 1 $ i2 $end
$var wire 1 % i3 $end
$var wire 1 & i4 $end
$var wire 1 ' i5 $end
$var wire 1 ( i6 $end
$var wire 1 ) i7 $end
$var wire 1 2 sel0 $end
$var wire 1 3 sel1 $end
$var wire 1 4 sel2 $end
$var wire 1 6 y_out $end
$var wire 1 S y_M1 $end
$var wire 1 T y_M0 $end
$scope module M0 $end
$var wire 1 0 i0 $end
$var wire 1 1 i1 $end
$var wire 1 $ i2 $end
$var wire 1 % i3 $end
$var wire 1 2 sel0 $end
$var wire 1 3 sel1 $end
$var wire 1 T y_out $end
$var wire 1 U y_M1 $end
$var wire 1 V y_M0 $end
$scope module M0 $end
$var wire 1 1 i0 $end
$var wire 1 0 i1 $end
$var wire 1 3 sel $end
$var wire 1 W sel_bar $end
$var wire 1 X y0 $end
$var wire 1 Y y1 $end
$var wire 1 V y_out $end
$upscope $end
$scope module M1 $end
$var wire 1 % i0 $end
$var wire 1 $ i1 $end
$var wire 1 3 sel $end
$var wire 1 Z sel_bar $end
$var wire 1 [ y0 $end
$var wire 1 \ y1 $end
$var wire 1 U y_out $end
$upscope $end
$scope module M2 $end
$var wire 1 U i0 $end
$var wire 1 U i1 $end
$var wire 1 2 sel $end
$var wire 1 ] sel_bar $end
$var wire 1 ^ y0 $end
$var wire 1 _ y1 $end
$var wire 1 T y_out $end
$upscope $end
$upscope $end
$scope module M1 $end
$var wire 1 & i0 $end
$var wire 1 ' i1 $end
$var wire 1 ( i2 $end
$var wire 1 ) i3 $end
$var wire 1 2 sel0 $end
$var wire 1 3 sel1 $end
$var wire 1 S y_out $end
$var wire 1 ` y_M1 $end
$var wire 1 a y_M0 $end
$scope module M0 $end
$var wire 1 ' i0 $end
$var wire 1 & i1 $end
$var wire 1 3 sel $end
$var wire 1 b sel_bar $end
$var wire 1 c y0 $end
$var wire 1 d y1 $end
$var wire 1 a y_out $end
$upscope $end
$scope module M1 $end
$var wire 1 ) i0 $end
$var wire 1 ( i1 $end
$var wire 1 3 sel $end
$var wire 1 e sel_bar $end
$var wire 1 f y0 $end
$var wire 1 g y1 $end
$var wire 1 ` y_out $end
$upscope $end
$scope module M2 $end
$var wire 1 ` i0 $end
$var wire 1 ` i1 $end
$var wire 1 2 sel $end
$var wire 1 h sel_bar $end
$var wire 1 i y0 $end
$var wire 1 j y1 $end
$var wire 1 S y_out $end
$upscope $end
$upscope $end
$scope module M2 $end
$var wire 1 S i0 $end
$var wire 1 T i1 $end
$var wire 1 4 sel $end
$var wire 1 k sel_bar $end
$var wire 1 l y0 $end
$var wire 1 m y1 $end
$var wire 1 6 y_out $end
$upscope $end
$upscope $end
$scope module M2 $end
$var wire 1 6 i0 $end
$var wire 1 7 i1 $end
$var wire 1 5 sel $end
$var wire 1 n sel_bar $end
$var wire 1 o y0 $end
$var wire 1 p y1 $end
$var wire 1 ! y_out $end
$upscope $end
$upscope $end
$upscope $end
$enddefinitions $end
#0
$dumpvars
0p
0o
1n
0m
0l
1k
0j
0i
1h
0g
0f
1e
0d
0c
1b
0a
0`
0_
0^
1]
0\
0[
1Z
0Y
0X
1W
0V
0U
0T
0S
0R
0Q
1P
0O
0N
1M
0L
0K
1J
0I
0H
1G
0F
0E
0D
0C
1B
0A
0@
1?
0>
0=
1<
0;
0:
09
08
07
06
05
04
03
02
01
00
0/
0.
0-
0,
0+
0*
0)
0(
0'
0&
0%
0$
0#
0"
0!
$end
#5000
1!
1o
16
1l
1S
1i
1`
1f
1)
#10000
0!
0o
06
0l
0S
0i
0`
0f
0)
1(
#15000
1!
1o
16
1l
1S
1i
1`
1a
1f
1c
1)
1'
#20000
0!
0o
06
0l
0S
0i
0`
0f
0)
0(
1&
#25000
1!
1o
16
1l
1S
1T
1i
1^
1`
1V
1U
1f
1X
1[
1)
11
1%
#30000
0!
0o
06
0l
0S
0i
0`
0a
0f
0c
0)
1(
0'
1$
#35000
1!
1o
16
1l
1S
1i
1`
1f
1)
#40000
0!
0o
06
0l
0S
0i
0`
0f
0)
0(
0&
10
#45000
1!
1o
16
17
1l
1Q
1S
18
1i
1N
1`
1a
1E
1f
1c
1K
1)
1'
1/
#50000
0!
0o
06
0l
0S
0T
0i
0^
0`
0V
0U
0f
0X
0[
0)
1(
01
0%
1.
#55000
1!
1o
16
1l
1S
1i
1`
1F
1f
1H
1)
1-
#60000
0!
0o
06
0l
0S
0i
0`
0a
0f
0c
0)
0(
0'
1&
0$
1,
#65000
1!
1o
16
1l
1S
19
1i
1C
1`
1:
1f
1@
1)
1+
#70000
0!
0o
06
0l
0S
0i
0`
0f
0)
1(
1*
#75000
1!
1o
16
1l
1S
1T
1i
1^
1`
1a
1V
1U
1;
1f
1c
1X
1[
1=
1)
1'
11
1%
1#
#80000
0!
0o
06
0l
0S
0i
0`
0f
0)
0(
0&
00
1"
#85000
1!
1o
16
1l
1S
1j
1`
0C
0N
0^
1f
0B
1D
0M
1O
0]
1_
0h
1)
12
#90000
0V
0a
0=
0@
0H
0X
0[
0f
0c
0K
0<
1>
0?
1A
0G
1I
0J
1L
0W
0Z
1\
0b
0e
1g
0)
1(
0'
1$
0/
13
#95000
0Q
0l
0P
1R
0k
1m
1)
14
#100000
0S
08
0j
0O
0`
1a
0E
0o
0g
1d
0L
0n
1p
0)
0(
1&
01
0%
0.
15
#105000
1)
1'
#110000
1S
1j
1`
1g
0)
1(
0-
#115000
1)
#120000
06
0m
0S
0T
0j
0_
0`
0a
0U
1V
0F
0g
0d
0\
1Y
0I
0)
0(
0'
0&
0$
10
0,
#125000
1)
11
1%
#130000
1S
1j
1`
1g
0)
1(
0+
#135000
1)
1'
1/
#140000
0!
0p
07
0R
0S
09
0j
0D
0`
1a
0:
0g
1d
0A
0)
0(
1&
0*
#145000
1)
#150000
16
1m
1S
1T
18
1j
1_
1O
1`
1U
1E
1g
1\
1L
0)
1(
0'
01
0%
1$
1.
0#
#155000
1)
#160000
0S
0j
0`
0a
0V
0;
0g
0d
0Y
0>
0)
0(
0&
00
0"
#165000
1)
1'
1-
#170000
1S
16
1i
1m
1`
1N
18
1^
1T
1g
1B
1M
0O
1]
0_
1h
0)
1(
02
#175000
1)
11
1%
#180000
16
1m
08
1T
0S
1F
0N
1V
1^
0i
1H
0E
1X
1[
1U
0`
1<
1?
1G
1J
0L
1W
1Z
0\
1b
1e
0g
0)
0(
0'
1&
0$
0/
1,
03
#185000
1S
1i
1`
1f
1)
#190000
0S
0i
0`
0l
06
0f
1P
1k
0m
0)
1(
04
#195000
16
1l
1S
19
1i
1C
1`
1a
1:
1f
1c
1@
1)
1'
1+
#200000
06
0l
0S
0T
0i
0^
0!
0`
0V
0U
0o
0f
0X
0[
1n
0)
0(
0&
01
0%
10
0.
05
#205000
1!
1o
16
1l
1S
1i
1`
1f
1)
#210000
0!
0o
06
0l
0S
0i
0`
0a
0f
0c
0)
1(
0'
1$
1*
#215000
1!
1o
16
1l
1S
1i
1`
1f
1)
#220000
0!
0o
06
0l
0S
0i
0`
0F
0f
0H
0)
0(
1&
0-
#225000
1!
1o
16
17
1l
1Q
1S
1T
18
1i
1^
1N
1`
1a
1V
1U
1E
1;
1f
1c
1X
1[
1K
1=
1)
1'
11
1%
1/
1#
#230000
0!
0o
06
0l
0S
0i
0`
0f
0)
1(
#235000
1!
1o
16
1l
1S
1i
1`
1f
1)
#240000
0!
0o
06
0l
0S
0i
0`
0a
0f
0c
0)
0(
0'
0&
0$
00
0,
1"
#245000
1!
1o
16
1l
1S
1i
1`
1f
1)
#250000
0!
0o
06
0l
0S
0T
0i
0^
0`
0V
0U
0f
0X
0[
0)
1(
01
0%
1.
#255000
1!
1o
16
1l
1S
1j
1`
1a
0C
0N
1f
1c
0B
1D
0M
1O
0]
0h
1)
1'
12
#260000
0!
0o
06
0l
0S
09
0j
0D
0`
0:
0f
0@
0)
0(
1&
0+
#265000
1!
1o
16
1l
1S
1j
1`
1f
1)
#270000
19
1T
1D
1_
0=
1:
1U
0f
0c
0K
0<
1>
0?
1A
0G
0J
1L
0W
0Z
1\
0b
1d
0e
1g
0)
1(
0'
1$
0/
13
#275000
1)
11
1%
1-
#280000
0!
0o
06
0l
0S
09
0j
0D
0`
0a
1V
0:
0g
0d
1Y
0A
0)
0(
0&
10
0*
#285000
1!
07
1o
0Q
16
0P
0k
1m
1)
1'
14
#290000
1S
1j
1`
1g
0)
1(
#295000
1)
#300000
06
0m
0S
0T
08
0j
0_
0O
0!
0`
1a
0U
0E
1F
0o
0g
1d
0\
0L
1I
0n
0)
0(
0'
1&
01
0%
0$
0.
1,
0#
15
#305000
1)
#310000
1S
1j
1`
1g
0)
1(
#315000
1)
1'
1/
#320000
0S
0j
0`
0a
0V
0;
0g
0d
0Y
0>
0)
0(
0&
00
0"
#325000
1)
11
1%
1+
#330000
16
1m
1S
1T
1j
1_
1`
1U
1g
1\
0)
1(
0'
1$
0-
#335000
1)
#340000
16
1m
0`
1a
1^
1T
0i
0S
0g
1d
1B
1M
1]
0_
1h
0j
0)
0(
1&
02
#345000
1)
1'
#350000
1!
1p
17
1R
1S
18
19
1i
1N
1C
1`
1E
1:
1g
1L
1A
0)
1(
01
0%
1.
1*
#355000
1)
#360000
1!
1p
17
06
1R
0m
19
08
0T
0S
1C
0N
0^
0i
1@
1:
0F
0E
0U
0a
0`
1<
1?
0A
1G
0I
1J
0L
1W
1Z
0\
1b
0d
1e
0g
0)
0(
0'
0&
0$
10
0/
0,
03
#365000
1S
1i
1`
1f
1)
#370000
0S
0i
0`
0f
0)
1(
#375000
16
1m
1S
1T
1i
1^
1`
1a
1V
1U
1;
1f
1c
1X
1[
1=
1)
1'
11
1%
1#
#380000
0S
0!
0i
0p
0`
07
0l
06
0f
1P
0R
1k
0m
0)
0(
1&
04
#385000
16
1l
1S
1i
1`
1F
1f
1H
1)
1-
#390000
06
0l
0S
09
0i
0C
0`
0a
0:
0f
0c
0@
0)
1(
0'
1$
0+
#395000
16
1l
1S
1i
1`
1f
1)
#400000
06
0l
0S
0T
0i
0^
0!
0`
0V
0U
0o
0f
0X
0[
1n
0)
0(
0&
01
0%
00
0.
1"
05
#405000
1!
1o
16
17
1l
1Q
1S
18
1i
1N
1`
1a
1E
1f
1c
1K
1)
1'
1/
#410000
0!
0o
06
0l
0S
0i
0`
0f
0)
1(
#415000
1!
1o
16
1l
1S
1i
1`
1f
1)
#420000
0!
0o
06
0l
0S
0i
0`
0a
0f
0c
0)
0(
0'
1&
0$
1,
0*
#425000
1!
1o
16
1l
1S
1T
1j
1_
1`
1V
1U
0N
1f
1X
1[
0B
0M
1O
0]
0h
1)
11
1%
12
#430000
0!
0o
06
0l
0S
0j
0`
0f
0)
1(
#435000
1!
1o
16
1l
1S
1j
1`
1a
1f
1c
1)
1'
#440000
0!
0o
06
0l
0S
0j
0`
0F
0f
0H
0)
0(
0&
10
0-
#445000
1!
1o
16
1l
1S
1j
1`
1f
1)
#450000
0a
1F
0f
0c
0X
0[
0K
0=
0<
1>
0?
0G
1I
0J
1L
0W
1Y
0Z
1\
0b
0e
1g
0)
1(
0'
01
0%
1$
0/
1.
0#
13
#455000
1)
1+
#460000
0!
0o
06
0l
0S
0j
0`
1a
0g
1d
0)
0(
1&
#465000
1)
1'
#470000
1!
1o
16
1l
1S
1j
1`
1g
0)
1(
#475000
07
0Q
0l
0P
0k
1m
1)
11
1%
14
#480000
0!
0o
06
0m
0S
0T
0j
0_
0`
0a
0U
0V
0F
0;
0g
0d
0\
0Y
0I
0>
0)
0(
0'
0&
0$
00
0,
0"
#485000
1)
#490000
17
1R
1S
19
1j
1D
1`
1:
1g
1A
0)
1(
1*
#495000
1)
1'
1/
1-
#500000
0S
08
0j
0O
0`
1a
0E
1!
0g
1d
0L
0n
1p
0)
0(
1&
01
0%
0.
15
